ml_eval_viz/__init__.py
ml_eval_viz/metrics.py
ml_eval_viz/plots.py
ml_eval_viz/sklearn_helpers.py
ml_eval_viz-0.4.0.dist-info/LICENSE
ml_eval_viz-0.4.0.dist-info/METADATA
ml_eval_viz-0.4.0.dist-info/WHEEL
ml_eval_viz-0.4.0.dist-info/RECORD
