Metadata-Version: 2.3
Name: ml_eval_viz
Version: 0.4.0
Summary: A custom python package for Machine Learning model evaluation and visualization.
License: MIT
Author: Vaibhav Kiran Ghaisas
Requires-Python: >=3.11.4,<4.0.0
Classifier: License :: OSI Approved :: MIT License
Classifier: Programming Language :: Python :: 3
Classifier: Programming Language :: Python :: 3.12
Classifier: Programming Language :: Python :: 3.13
Requires-Dist: matplotlib (>=3.10.5,<4.0.0)
Requires-Dist: numpy (>=2.3.2,<3.0.0)
Requires-Dist: pandas (==2.2.2)
Requires-Dist: scikit-learn (==1.5.1)
